autologin_middleware/__init__.py
autologin_middleware/middleware.py
autologin_middleware/splash.py
autologin_middleware/utils.py
autologin_middleware-0.1.5.dist-info/DESCRIPTION.rst
autologin_middleware-0.1.5.dist-info/METADATA
autologin_middleware-0.1.5.dist-info/RECORD
autologin_middleware-0.1.5.dist-info/WHEEL
autologin_middleware-0.1.5.dist-info/metadata.json
autologin_middleware-0.1.5.dist-info/top_level.txt
