Metadata-Version: 2.0
Name: autologin-middleware
Version: 0.1.5
Summary: A Scrapy middleware to use with autologin
Home-page: https://github.com/TeamHG-Memex/autologin-middleware
Author: Konstantin Lopuhin, Mikhail Korobov
Author-email: kostia.lopuhin@gmail.com
License: MIT
Platform: UNKNOWN
Classifier: Development Status :: 3 - Alpha
Classifier: Topic :: Internet :: WWW/HTTP :: Indexing/Search
Classifier: License :: OSI Approved :: MIT License
Classifier: Programming Language :: Python
Classifier: Programming Language :: Python :: 2
Classifier: Programming Language :: Python :: 2.7
Classifier: Programming Language :: Python :: 3
Classifier: Programming Language :: Python :: 3.3
Classifier: Programming Language :: Python :: 3.4
Classifier: Programming Language :: Python :: 3.5
Requires-Dist: scrapy (>=1.1.0)
Requires-Dist: six
